tegregr/__init__.py
tegregr-0.1.4.dist-info/LICENSE
tegregr-0.1.4.dist-info/METADATA
tegregr-0.1.4.dist-info/WHEEL
tegregr-0.1.4.dist-info/top_level.txt
tegregr-0.1.4.dist-info/RECORD
