Metadata-Version: 2.1
Name: tegregr
Version: 0.1.4
Summary: Multiple and hierarchical regression
Home-page: https://github.com/thomasgladwin/tegregr
Author: Thomas E Gladwin
Author-email: thomasgladwin@hotmail.com
License: UNKNOWN
Platform: UNKNOWN
Classifier: Programming Language :: Python :: 3
Classifier: License :: OSI Approved :: MIT License
Classifier: Operating System :: OS Independent
Requires-Python: >=3.6
